pypint_setup.py
pypint/__init__.py
pypint/cfg.py
pypint/console.py
pypint/model.py
pypint/tools.py
pypint/types.py
pypint/ui.py
pypint/utils.py
pypint/converters/__init__.py
pypint/converters/biocham.py
pypint/converters/cadbiom.py
pypint/converters/minibn.py
pypint/converters/sbgnpd.py
pypint/converters/lib/__init__.py
pypint/converters/lib/boolean_utils.py
pypint/converters/lib/export_utils.py
pypint/converters/lib/sbgnpd.py
pypint-1.6.4.dist-info/METADATA
pypint-1.6.4.dist-info/WHEEL
pypint-1.6.4.dist-info/entry_points.txt
pypint-1.6.4.dist-info/top_level.txt
pypint-1.6.4.dist-info/RECORD
